sgd_dstc8_data_model/__init__.py
sgd_dstc8_data_model/dstc_constants.py
sgd_dstc8_data_model/dstc_dataclasses.py
sgd_dstc8_data_model/dstc_utils.py
sgd_dstc8_data_model/example.py
sgd_dstc8_data_model-0.2.0.dist-info/LICENSE
sgd_dstc8_data_model-0.2.0.dist-info/METADATA
sgd_dstc8_data_model-0.2.0.dist-info/WHEEL
sgd_dstc8_data_model-0.2.0.dist-info/entry_points.txt
sgd_dstc8_data_model-0.2.0.dist-info/RECORD
